demo/__init__.py
demo/fabfile.py
demo/manage.py
demo/requirements.txt
demo/example/__init__.py
demo/example/settings.py
demo/example/urls.py
demo/example/wsgi.py
demo/example/foo/__init__.py
demo/example/foo/forms.py
demo/example/foo/models.py
demo/example/foo/tests.py
demo/example/foo/urls.py
demo/example/foo/validators.py
demo/example/foo/views.py
demo/example/foo/fixtures/initial_data.json
demo/example/foo/migrations/0001_initial.py
demo/example/foo/migrations/__init__.py
demo/example/foo/templates/foo/foo_confirm_delete.html
demo/example/foo/templates/foo/foo_form.html
demo/example/foo/templates/foo/foo_list.html
demo/example/locale/en/LC_MESSAGES/django.mo
demo/example/locale/en/LC_MESSAGES/django.po
demo/example/locale/pl/LC_MESSAGES/django.mo
demo/example/locale/pl/LC_MESSAGES/django.po
demo/example/locale/pt_BR/LC_MESSAGES/django.mo
demo/example/locale/pt_BR/LC_MESSAGES/django.po
demo/example/locale/ru/LC_MESSAGES/django.mo
demo/example/locale/ru/LC_MESSAGES/django.po
demo/example/sample_plans/__init__.py
demo/example/sample_plans/admin.py
demo/example/sample_plans/apps.py
demo/example/sample_plans/models.py
demo/example/sample_plans/tests.py
demo/example/sample_plans/fixtures/initial_plan.json
demo/example/sample_plans/fixtures/test_django-plans_auth.json
demo/example/sample_plans/fixtures/test_django-plans_default_plans.json
demo/example/sample_plans/fixtures/test_django-plans_plans.json
demo/example/sample_plans/management/__init__.py
demo/example/sample_plans/management/commands/__init__.py
demo/example/sample_plans/management/commands/autorenew_accounts.py
demo/example/sample_plans/management/commands/create_userplans.py
demo/example/sample_plans/management/commands/expire_accounts.py
demo/example/sample_plans/migrations/0001_initial.py
demo/example/sample_plans/migrations/__init__.py
demo/example/sample_plans/templates/mail/change_plan_body.txt
demo/example/sample_plans/templates/mail/change_plan_title.txt
django_plans-2.0.0.dist-info/AUTHORS
django_plans-2.0.0.dist-info/LICENSE
django_plans-2.0.0.dist-info/METADATA
django_plans-2.0.0.dist-info/WHEEL
django_plans-2.0.0.dist-info/top_level.txt
django_plans-2.0.0.dist-info/RECORD
