Metadata-Version: 2.1
Name: django-plans
Version: 2.0.0
Summary: Pluggable django app for managing pricing plans with quotas and accounts expiration
Home-page: https://github.com/cypreess/django-plans
Author: Krzysztof Dorosz
Author-email: cypreess@gmail.com
License: MIT
Classifier: Development Status :: 5 - Production/Stable
Classifier: Framework :: Django
Classifier: Intended Audience :: Developers
Classifier: License :: OSI Approved :: BSD License
Classifier: Operating System :: OS Independent
Classifier: Programming Language :: Python
Classifier: Programming Language :: Python :: 3.9
Classifier: Programming Language :: Python :: 3.10
Classifier: Programming Language :: Python :: 3.11
Classifier: Programming Language :: Python :: 3.12
Classifier: Programming Language :: Python :: 3.13
License-File: LICENSE
License-File: AUTHORS
Requires-Dist: django-countries (>=4.5)
Requires-Dist: pytz (>=2017.2)
Requires-Dist: django-ordered-model (>=1.4.1)
Requires-Dist: python-stdnum
Requires-Dist: django-next-url-mixin (>=0.1.0)
Requires-Dist: suds
Requires-Dist: django-sequences
Requires-Dist: swapper (~=1.3.0)
Requires-Dist: six
Provides-Extra: i18n
Requires-Dist: django-modeltranslation (>=0.5b1) ; extra == 'i18n'
